gish/__init__.py
gish/cli.py
gish/config.py
gish/profiles.py
gish-1.0.7.dist-info/METADATA
gish-1.0.7.dist-info/WHEEL
gish-1.0.7.dist-info/entry_points.txt
gish-1.0.7.dist-info/top_level.txt
gish-1.0.7.dist-info/RECORD
