Metadata-Version: 2.1
Name: gish
Version: 1.0.7
Summary: A CLI tool for managing GitHub profiles using SSH.
Home-page: https://github.com/helder-avynta/gish
Author: Helder Perez
Author-email: helder.perez@avynta.com
Classifier: Development Status :: 3 - Alpha
Classifier: Intended Audience :: Developers
Classifier: License :: OSI Approved :: MIT License
Classifier: Programming Language :: Python :: 3
Classifier: Programming Language :: Python :: 3.7
Classifier: Programming Language :: Python :: 3.8
Classifier: Programming Language :: Python :: 3.9
Classifier: Programming Language :: Python :: 3.10
Requires-Python: >=3.7
Requires-Dist: click
